bambu_server/__init__.py
bambu_server/config.py
bambu_server/routes.py
bambu_server/server.py
bambu_server/worker.py
bambu_server/static/js/jsme/34E2FA2BF557CF0A2AD31C564BD08F6C.cache.js
bambu_server/static/js/jsme/396F806CD63ABD414BFBB9D57429F05B.cache.png
bambu_server/static/js/jsme/3C274776FA3E1CD82BBFDD5A9898856E.cache.js
bambu_server/static/js/jsme/3D67E597FCB4058FA8D1958C27CA53FA.cache.js
bambu_server/static/js/jsme/40BAF81124143A595056A9CCA0E9DBBA.cache.png
bambu_server/static/js/jsme/4841BDE9DC293BA35F7762B4D8EFD236.cache.png
bambu_server/static/js/jsme/5487824B32631D972DE489C7F91B8074.cache.js
bambu_server/static/js/jsme/59695728B231CCB18E4D83152D497ABF.cache.js
bambu_server/static/js/jsme/7ACE5577313D4A11E87C1216B098DB3A.cache.js
bambu_server/static/js/jsme/8508C994125211B70C8DC6A6B3128C9F.cache.js
bambu_server/static/js/jsme/96E40B969193BD74B8A621486920E79C.cache.js
bambu_server/static/js/jsme/A6DBDE07E3A8F66E8959A4F32505E16B.cache.png
bambu_server/static/js/jsme/A6F07BEC1B1688C12F5B955C842A4E18.cache.js
bambu_server/static/js/jsme/C10E29B5EC0A8B8F17E4DBDDCCB182D9.cache.js
bambu_server/static/js/jsme/C792BDF2252D1321650288B17D5C7FA9.cache.js
bambu_server/static/js/jsme/DF7764EEC1903CD03C9545B354D8D8E4.cache.png
bambu_server/static/js/jsme/E2151234309C74611B542B69A5371ABB.cache.js
bambu_server/static/js/jsme/F96AE52F373689A640D6534B99783720.cache.js
bambu_server/static/js/jsme/clear.cache.gif
bambu_server/static/js/jsme/compilation-mappings.txt
bambu_server/static/js/jsme/jsa.css
bambu_server/static/js/jsme/jsme.devmode.js
bambu_server/static/js/jsme/jsme.nocache.js
bambu_server/static/js/jsme/deferredjs/34E2FA2BF557CF0A2AD31C564BD08F6C/1.cache.js
bambu_server/static/js/jsme/deferredjs/34E2FA2BF557CF0A2AD31C564BD08F6C/10.cache.js
bambu_server/static/js/jsme/deferredjs/34E2FA2BF557CF0A2AD31C564BD08F6C/11.cache.js
bambu_server/static/js/jsme/deferredjs/34E2FA2BF557CF0A2AD31C564BD08F6C/2.cache.js
bambu_server-0.0.2.dist-info/LICENSE
bambu_server-0.0.2.dist-info/METADATA
bambu_server-0.0.2.dist-info/WHEEL
bambu_server-0.0.2.dist-info/entry_points.txt
bambu_server-0.0.2.dist-info/top_level.txt
bambu_server-0.0.2.dist-info/RECORD
