Metadata-Version: 2.1
Name: bambu-server
Version: 0.0.2
Summary: bambu-server: model provisiong tool for Bambu
Author: Frederico Schmitt Kremer
Author-email: leitzke.gi@gmail.com, fred.s.kremer@gmail.com
Keywords: bioinformatics machine-learning data science drug discovery QSAR
License-File: LICENSE
Requires-Dist: bambu-qsar
Requires-Dist: gunicorn
Requires-Dist: yagmail
Requires-Dist: flask
Requires-Dist: flask-sqlalchemy
Requires-Dist: celery
Requires-Dist: python-dotenv
Requires-Dist: redis
Requires-Dist: twine
